gavelgen/__init__.py
gavelgen/gavel.py
gavelgen-0.1.6.dist-info/METADATA
gavelgen-0.1.6.dist-info/WHEEL
gavelgen-0.1.6.dist-info/top_level.txt
gavelgen-0.1.6.dist-info/RECORD
